lazytree/__init__.py
lazytree/lazytree.py
lazytree/test_lazytree.py
lazytree-0.3.4.dist-info/LICENSE
lazytree-0.3.4.dist-info/METADATA
lazytree-0.3.4.dist-info/WHEEL
lazytree-0.3.4.dist-info/RECORD
