Metadata-Version: 2.1
Name: lazytree
Version: 0.3.4
Summary: Python library for manipulating infinite trees.
Home-page: https://github.com/mvcisback/pyLazyTree
License: MIT
Author: Marcell Vazquez-Chanlatte
Author-email: marcell.vc@eecs.berkeley.edu
Requires-Python: >=3.6,<4.0
Classifier: License :: OSI Approved :: MIT License
Classifier: Programming Language :: Python :: 3
Classifier: Programming Language :: Python :: 3.6
Classifier: Programming Language :: Python :: 3.7
Classifier: Programming Language :: Python :: 3.8
Classifier: Programming Language :: Python :: 3.9
Classifier: Programming Language :: Python :: 3.10
Classifier: Programming Language :: Python :: 3.11
Requires-Dist: attrs (>=22.0.0,<23.0.0)
Requires-Dist: funcy (>=1.12,<2.0)
Project-URL: Repository, https://github.com/mvcisback/pyLazyTree
